forgen/__init__.py
forgen/agent/__init__.py
forgen/agent/agent.py
forgen/agent/helper.py
forgen/agent/test.py
forgen/agent/examples/__init__.py
forgen/agent/examples/antecedent_basis_checker.py
forgen/agent/examples/arxiv_searcher.py
forgen/agent/examples/boilerplate_inserter_tool.py
forgen/agent/examples/chat_summarizer.py
forgen/agent/examples/coding_agents.py
forgen/agent/examples/doc_summarizer.py
forgen/agent/examples/examiner_data_tool.py
forgen/agent/examples/infer_document_meta_info.py
forgen/agent/examples/input_chunker.py
forgen/agent/examples/map_merger.py
forgen/agent/examples/patent_intelligence_agent.py
forgen/agent/examples/pub_med_searcher.py
forgen/agent/examples/ref_numeral_extractor.py
forgen/agent/examples/reference_summarizer_node.py
forgen/agent/examples/semantic_scholar_searcher.py
forgen/agent/examples/text_gloss_generator.py
forgen/agent/examples/url_summarizer.py
forgen/agent/examples/cognitive_agent/__init__.py
forgen/agent/examples/cognitive_agent/cog_agent_general_url.py
forgen/agent/examples/patent_tools/__init__.py
forgen/agent/examples/patent_tools/ads_form_generator.py
forgen/agent/examples/patent_tools/background_generator.py
forgen/agent/examples/patent_tools/draft_spec_mapper.py
forgen/agent/examples/patent_tools/filing_checklist_generator.py
forgen/agent/examples/patent_tools/ids_compliance_checker.py
forgen/agent/examples/patent_tools/ids_form_generator.py
forgen/agent/examples/patent_tools/ir_assignment_recommender.py
forgen/agent/examples/patent_tools/ir_innovation_analyzer.py
forgen/agent/examples/patent_tools/ir_metadata_extractor.py
forgen/agent/examples/patent_tools/ir_prior_art_assessor.py
forgen/agent/examples/patent_tools/ir_tech_classifier.py
forgen/agent/examples/patent_tools/parts_list_extractor.py
forgen/agent/examples/patent_tools/patent_claims_drafter.py
forgen/agent/examples/patent_tools/patent_summary_generator.py
forgen/agent/examples/tools/__init__.py
forgen/agent/examples/tools/batch_tool_processor.py
forgen-0.1.8.dist-info/licenses/LICENSE
forgen-0.1.8.dist-info/METADATA
forgen-0.1.8.dist-info/WHEEL
forgen-0.1.8.dist-info/top_level.txt
forgen-0.1.8.dist-info/RECORD
