Metadata-Version: 2.4
Name: forgen
Version: 0.1.8
Summary: A modular framework for building generative AI wrapper components, including generative tools, pipelines, and agents.
Home-page: https://forgen.ai
Author: ForGen AI, LLC
Author-email: support@forgen.ai
License: Proprietary
Classifier: License :: Other/Proprietary License
Classifier: Programming Language :: Python :: 3
Classifier: Programming Language :: Python :: 3.12
Classifier: Operating System :: OS Independent
Requires-Python: >=3.8
License-File: LICENSE
Requires-Dist: boto3<2.0,>=1.35
Requires-Dist: requests<3.0,>=2.32
Requires-Dist: chardet<6.0,>=5.2
Requires-Dist: docx2txt<1.0,>=0.9
Requires-Dist: pandas<3.0,>=2.2
Requires-Dist: pytesseract<1.0,>=0.3.13
Requires-Dist: pypdf<5.0,>=4.3
Requires-Dist: beautifulsoup4<5.0,>=4.12
Requires-Dist: striprtf<1.0,>=0.0.29
Requires-Dist: pillow<12.0,>=11.1
Requires-Dist: reportlab<5.0,>=4.3
Requires-Dist: pdf2image<2.0,>=1.17
Requires-Dist: python-dotenv<2.0,>=1.0
Requires-Dist: openai>=1.73
Requires-Dist: anthropic
Requires-Dist: feedparser<7.0,>=6.0
Requires-Dist: tiktoken<1.0,>=0.8
Requires-Dist: setuptools>=75.8
Requires-Dist: pypandoc<2.0,>=1.15
Requires-Dist: langchain-text-splitters<1.0,>=0.3
Dynamic: author
Dynamic: author-email
Dynamic: classifier
Dynamic: description-content-type
Dynamic: home-page
Dynamic: license
Dynamic: license-file
Dynamic: requires-dist
Dynamic: requires-python
Dynamic: summary
